{
  "generated_at": "2026-03-31T09:19:06.966811+00:00",
  "valid_until": "2026-04-01T09:19:06.966811+00:00",
  "regime": "RANGE",
  "confidence": 0.9095,
  "classifier": "RandomForest+Markov (n=279 samples)",
  "strategy_overrides": {
    "breakout": true,
    "momentum": true,
    "kalman_regime": true,
    "mean_reversion": false,
    "vwap": false,
    "mini_medallion": true
  },
  "diagnostics": {
    "adx_14": 31.809559,
    "atr_pct": 0.037025,
    "bb_width_ratio": 1.656734,
    "close_ema20_pct": -0.022995,
    "momentum_1d": 0.012681,
    "momentum_5d": 0.020847,
    "range_atr_ratio": 0.819127,
    "vol_ratio": 0.118412,
    "park_vol_zscore": -0.318217
  },
  "strategy_weights": {
    "breakout": 0.6,
    "momentum": 0.55,
    "kalman_regime": 0.75,
    "mean_reversion": 0.0,
    "vwap": 0.0,
    "mini_medallion": 0.6
  },
  "performance_scores": {
    "kalman_regime": -0.16,
    "mini_medallion": -0.2038,
    "vwap_deviation": -0.3102
  },
  "regime_probabilities": {
    "TREND": 0.0833,
    "RANGE": 0.9095,
    "VOLATILE": 0.0072
  },
  "transition_matrix": {
    "TREND": {
      "TREND": 0.1613,
      "RANGE": 0.7097,
      "VOLATILE": 0.129
    },
    "RANGE": {
      "TREND": 0.1,
      "RANGE": 0.892,
      "VOLATILE": 0.008
    },
    "VOLATILE": {
      "TREND": 0.1429,
      "RANGE": 0.7143,
      "VOLATILE": 0.1429
    }
  }
}